{
  "version": "2.2.4",
  "songName": "Gooey",
  "artist": "LeGooey",
  "charter": "LeGooey",
  "timeFormat": "ms",
  "divisions": 96,
  "offsets": {"instrumental": 0},
  "timeChanges": [{ "t": 0, "bpm": 150, "n": 4, "d": 4, "bt": [4, 4, 4, 4] }],
  "looped": false,
  "playData": {
    "songVariations": [],
    "difficulties": ["easy", "normal", "hard"],
    "characters": {
      "player": "bf","girlfriend": "gf","opponent": "gooey-opponent",
      "instrumental": "","playerVocals": ["bf"],"opponentVocals": ["gooey"], "altInstrumentals": []
    },
    "stage": "hotelCastle",
    "noteStyle": "funkin",
    "ratings": { "easy": 2, "normal": 3, "hard": 4 },
    "album": "gooeymix2",
    "stickerPack": "bonus-gooeyWeekBf"
  },
  "previewStart": 0,
  "previewEnd": 15000,
  "generatedBy": "LeGooey (by hand)"
}